ruly/__init__.py
ruly/common.py
ruly/evaluator.py
ruly/knowledge_base.py
ruly/parser.py
ruly/version.py
ruly_zlatsic-0.0.1.dist-info/LICENSE
ruly_zlatsic-0.0.1.dist-info/METADATA
ruly_zlatsic-0.0.1.dist-info/WHEEL
ruly_zlatsic-0.0.1.dist-info/top_level.txt
ruly_zlatsic-0.0.1.dist-info/RECORD
