Metadata-Version: 2.1
Name: ruly-zlatsic
Version: 0.0.1
Summary: Simple, extensible rule engine in Python
Home-page: https://github.com/ZlatSic/ruly
Author: Zlatan Sičanica
Author-email: zlatan.sicanica@gmail.com
License: UNKNOWN
Platform: UNKNOWN
